jupyterlab_nbhosting/__init__.py
jupyterlab_nbhosting/_version.py
jupyterlab_nbhosting-0.5.5.data/data/share/jupyter/labextensions/jupyterlab-nbhosting/build_log.json
jupyterlab_nbhosting-0.5.5.data/data/share/jupyter/labextensions/jupyterlab-nbhosting/install.json
jupyterlab_nbhosting-0.5.5.data/data/share/jupyter/labextensions/jupyterlab-nbhosting/package.json
jupyterlab_nbhosting-0.5.5.data/data/share/jupyter/labextensions/jupyterlab-nbhosting/schemas/jupyterlab-nbhosting/package.json.orig
jupyterlab_nbhosting-0.5.5.data/data/share/jupyter/labextensions/jupyterlab-nbhosting/schemas/jupyterlab-nbhosting/plugin.json
jupyterlab_nbhosting-0.5.5.data/data/share/jupyter/labextensions/jupyterlab-nbhosting/schemas/jupyterlab-nbhosting/plugin.json.kernelname
jupyterlab_nbhosting-0.5.5.data/data/share/jupyter/labextensions/jupyterlab-nbhosting/schemas/jupyterlab-nbhosting/plugin.json.kernelname-notworking
jupyterlab_nbhosting-0.5.5.data/data/share/jupyter/labextensions/jupyterlab-nbhosting/static/lib_index_js.13ec67500ec74507d130.js
jupyterlab_nbhosting-0.5.5.data/data/share/jupyter/labextensions/jupyterlab-nbhosting/static/lib_index_js.13ec67500ec74507d130.js.map
jupyterlab_nbhosting-0.5.5.data/data/share/jupyter/labextensions/jupyterlab-nbhosting/static/lib_index_js.514d6a541d4ed26aac20.js
jupyterlab_nbhosting-0.5.5.data/data/share/jupyter/labextensions/jupyterlab-nbhosting/static/lib_index_js.514d6a541d4ed26aac20.js.map
jupyterlab_nbhosting-0.5.5.data/data/share/jupyter/labextensions/jupyterlab-nbhosting/static/lib_index_js.8f33fa9bed9cc8c260c1.js
jupyterlab_nbhosting-0.5.5.data/data/share/jupyter/labextensions/jupyterlab-nbhosting/static/lib_index_js.8f33fa9bed9cc8c260c1.js.map
jupyterlab_nbhosting-0.5.5.data/data/share/jupyter/labextensions/jupyterlab-nbhosting/static/remoteEntry.0188f0dbef6f2246f8c8.js.map
jupyterlab_nbhosting-0.5.5.data/data/share/jupyter/labextensions/jupyterlab-nbhosting/static/remoteEntry.0367ae2cb2418f14ea2a.js.map
jupyterlab_nbhosting-0.5.5.dist-info/METADATA
jupyterlab_nbhosting-0.5.5.dist-info/WHEEL
jupyterlab_nbhosting-0.5.5.dist-info/licenses/LICENSE
jupyterlab_nbhosting-0.5.5.dist-info/RECORD
