Metadata-Version: 2.1
Name: jupyterlab_nbhosting
Version: 0.5.5
Summary: Custom look and feel for nbhosting notebooks
Project-URL: Homepage, https://github.com/parmentelat/jupyterlab-nbhosting
Project-URL: Bug Tracker, https://github.com/parmentelat/jupyterlab-nbhosting/issues
Project-URL: Repository, https://github.com/parmentelat/jupyterlab-nbhosting.git
Author-email: Thierry Parmentelat <thierry.parmentelat@inria.fr>
License: BSD 3-Clause License
License-File: LICENSE
Classifier: Framework :: Jupyter
Classifier: Framework :: Jupyter :: JupyterLab
Classifier: Framework :: Jupyter :: JupyterLab :: 4
Classifier: Framework :: Jupyter :: JupyterLab :: Extensions
Classifier: Framework :: Jupyter :: JupyterLab :: Extensions :: Prebuilt
Classifier: License :: OSI Approved :: BSD License
Classifier: Programming Language :: Python
Classifier: Programming Language :: Python :: 3
Classifier: Programming Language :: Python :: 3.8
Classifier: Programming Language :: Python :: 3.9
Classifier: Programming Language :: Python :: 3.10
Classifier: Programming Language :: Python :: 3.11
Requires-Python: >=3.8
